README.rst
setup.cfg
setup.py
xiPy/__init__.py
xiPy/paho_mqtt_client.py
xiPy/xively_backoff.py
xiPy/xively_callback_handler.py
xiPy/xively_client.py
xiPy/xively_config.py
xiPy/xively_connection_parameters.py
xiPy/xively_error_codes.py
xiPy/xively_message.py
xiPy/xively_version.py
xiPy.egg-info/PKG-INFO
xiPy.egg-info/SOURCES.txt
xiPy.egg-info/dependency_links.txt
xiPy.egg-info/top_level.txt
xiPy.egg-info/zip-safe
xiPy/certs/GeoTrust Primary Certification Authority - G3.pem
xiPy/certs/GlobalSign Root CA.pem
xiPy/certs/VeriSign Class 3 Public Primary Certification Authority - G5.pem
xiPy/certs/thawte Primary Root CA - G3.pem
xiPy/licenses/LICENSE.md
xiPy/licenses/PAHO-MQTT-PYTHON-LICENSE.txt
xiPy/licenses/edl-v10
xiPy/licenses/epl-v10