Metadata-Version: 1.1
Name: xiPy
Version: 1.0.0rc1
Summary: Xively Client Python Library
Home-page: http://github.com/xively/xiPy
Author: Xively by LogMeIn, Inc.
Author-email: XivelyInfo@LogMeIn.com
License: BSD 3-Clause
Platform: UNKNOWN
Classifier: Programming Language :: Python :: 2.7
Classifier: Programming Language :: Python :: 3.4
Classifier: Programming Language :: Python :: 3.5
